{
    "name": "Spider-Man",
    "title_id": "41560006",
    "releases": [
        {
            "title_id": "41560006",
            "region": "USA",
            "edition": "Original",
            "disc_id": 1
        },
        {
            "title_id": "41560006",
            "region": "Europe",
            "edition": "Original",
            "disc_id": 2
        },
        {
            "title_id": "41560006",
            "region": "France",
            "edition": "Original",
            "disc_id": 3
        },
        {
            "title_id": "41560006",
            "region": "Germany",
            "edition": "Original",
            "disc_id": 4
        },
        {
            "title_id": "41560006",
            "region": "Korea",
            "edition": "Original",
            "disc_id": 5
        },
        {
            "title_id": "4343000a",
            "region": "Japan",
            "edition": "Original",
            "disc_id": 1
        }
    ]
}